{
  "abstract_method_signature": {
    "fields": {
      "accessibility_modifier": {},
      "override_modifier": {},
      "call_signature": {}
    }
  },
  "ambient_declaration": {
    "fields": {
      "declaration": {},
      "type": {},
      "semicolon": {}
    }
  },
  "as_expression": {
    "fields": {
      "expression": {},
      "type": {}
    }
  },
  "class_declaration": {
    "fields": {
      "class_heritage": {},
      "automatic_semicolon": {}
    }
  },
  "class_heritage": {
    "fields": {
      "extends_clause": {},
      "implements_clause": {}
    }
  },
  "enum_body": {
    "fields": {
      "opening": {},
      "members": {
        "multiple": true
      }
    }
  },
  "export_statement": {
    "fields": {
      "declaration": {},
      "source": {},
      "semicolon": {}
    }
  },
  "import_alias": {
    "fields": {
      "name": {},
      "value": {},
      "semicolon": {}
    }
  },
  "import_clause": {
    "fields": {
      "default_import": {},
      "named_imports": {}
    }
  },
  "import_statement": {
    "fields": {
      "import_clause": {},
      "from_clause": {},
      "import_attribute": {},
      "semicolon": {}
    }
  },
  "infer_type": {
    "fields": {
      "type_identifier": {},
      "type": {}
    }
  },
  "intersection_type": {
    "fields": {
      "left": {},
      "right": {}
    }
  },
  "lexical_declaration": {
    "fields": {
      "declarators": {
        "multiple": true
      },
      "semicolon": {}
    }
  },
  "lookup_type": {
    "fields": {
      "primary_type": {},
      "type": {}
    }
  },
  "method_definition": {
    "fields": {
      "accessibility_modifier": {},
      "override_modifier": {},
      "call_signature": {}
    }
  },
  "method_signature": {
    "fields": {
      "accessibility_modifier": {},
      "override_modifier": {},
      "call_signature": {}
    }
  },
  "object_type": {
    "fields": {
      "opening": {},
      "members": {
        "multiple": true
      },
      "closing": {}
    }
  },
  "optional_parameter": {
    "fields": {
      "parameter_name": {},
      "initializer": {}
    }
  },
  "program": {
    "fields": {
      "hash_bang_line": {},
      "statements": {
        "multiple": true
      }
    }
  },
  "property_signature": {
    "fields": {
      "accessibility_modifier": {},
      "override_modifier": {}
    }
  },
  "public_field_definition": {
    "fields": {
      "accessibility_modifier": {},
      "override_modifier": {},
      "initializer": {}
    }
  },
  "required_parameter": {
    "fields": {
      "parameter_name": {},
      "initializer": {}
    }
  },
  "satisfies_expression": {
    "fields": {
      "expression": {},
      "type": {}
    }
  },
  "statement_block": {
    "fields": {
      "statements": {
        "multiple": true
      },
      "automatic_semicolon": {}
    }
  },
  "type_assertion": {
    "fields": {
      "type_arguments": {},
      "expression": {}
    }
  },
  "union_type": {
    "fields": {
      "left": {},
      "right": {}
    }
  },
  "variable_declaration": {
    "fields": {
      "declarators": {
        "multiple": true
      },
      "semicolon": {}
    }
  }
}
